LICENSE
MANIFEST.in
README.rst
setup.py
il2fb/parsers/mission/__init__.py
il2fb/parsers/mission/constants.py
il2fb/parsers/mission/converters.py
il2fb/parsers/mission/exceptions.py
il2fb/parsers/mission/utils.py
il2fb/parsers/mission/sections/__init__.py
il2fb/parsers/mission/sections/base.py
il2fb/parsers/mission/sections/born_place.py
il2fb/parsers/mission/sections/buildings.py
il2fb/parsers/mission/sections/chiefs.py
il2fb/parsers/mission/sections/front_marker.py
il2fb/parsers/mission/sections/main.py
il2fb/parsers/mission/sections/mds.py
il2fb/parsers/mission/sections/nstationary.py
il2fb/parsers/mission/sections/respawn_time.py
il2fb/parsers/mission/sections/rocket.py
il2fb/parsers/mission/sections/season.py
il2fb/parsers/mission/sections/static_camera.py
il2fb/parsers/mission/sections/target.py
il2fb/parsers/mission/sections/weather.py
il2fb/parsers/mission/sections/wing.py
il2fb_mission_parser.egg-info/PKG-INFO
il2fb_mission_parser.egg-info/SOURCES.txt
il2fb_mission_parser.egg-info/dependency_links.txt
il2fb_mission_parser.egg-info/namespace_packages.txt
il2fb_mission_parser.egg-info/requires.txt
il2fb_mission_parser.egg-info/top_level.txt
requirements/dist.txt