Metadata-Version: 1.1
Name: il2fb-mission-parser
Version: 1.1.3
Summary: Parse IL-2 FB mission file and produce detailed information about mission.
Home-page: https://github.com/IL2HorusTeam/il2fb-mission-parser
Author: Alexander Oblovatniy, Alexander Kamyhin
Author-email: oblovatniy@gmail.com, kamyhin@gmail.com
License: LGPLv3
Keywords: il2,il-2,fb,forgotten battles,parser,mission
Platform: UNKNOWN
Classifier: Development Status :: 5 - Production/Stable
Classifier: Intended Audience :: Developers
Classifier: License :: OSI Approved :: GNU Lesser General Public License v3 (LGPLv3)
Classifier: Natural Language :: English
Classifier: Operating System :: Unix
Classifier: Operating System :: Microsoft :: Windows
Classifier: Programming Language :: Python :: 2.7
Classifier: Programming Language :: Python :: 3.4
Classifier: Programming Language :: Python :: 3.5
Classifier: Programming Language :: Python :: 3.6
Classifier: Topic :: Software Development :: Libraries
